AUTHORS
ChangeLog
LICENSE
README.en.md
README.md
requirement.txt
setup.cfg
setup.py
etc/cloudimg/aws/aws_aarch64.json
etc/cloudimg/aws/aws_x86_64.json
etc/cloudimg/aws/ena.ko
etc/cloudimg/aws/install_packages.txt
etc/cloudimg/aws/role-policy.json
etc/cloudimg/aws/trust-policy.json
etc/cloudimg/gen/gen.cfg
etc/cloudimg/gen/install_packages.txt
etc/cloudimg/script/aws_install.sh
etc/cloudimg/script/aws_resize.sh
etc/cloudimg/script/gen_install.sh
etc/container/ai/registry.yaml
etc/container/openeuler/Dockerfile
etc/container/openeuler/registry.yaml
etc/container/openeuler/tags.yaml
etc/picture/eulerpublisher.png
eulerpublisher/__init__.py
eulerpublisher/eulerpublisher.py
eulerpublisher.egg-info/PKG-INFO
eulerpublisher.egg-info/SOURCES.txt
eulerpublisher.egg-info/dependency_links.txt
eulerpublisher.egg-info/entry_points.txt
eulerpublisher.egg-info/not-zip-safe
eulerpublisher.egg-info/pbr.json
eulerpublisher.egg-info/top_level.txt
eulerpublisher/cloudimg/__init__.py
eulerpublisher/cloudimg/cli.py
eulerpublisher/cloudimg/aws/__init__.py
eulerpublisher/cloudimg/aws/aws.py
eulerpublisher/cloudimg/aws/cli.py
eulerpublisher/cloudimg/gen/__init__.py
eulerpublisher/cloudimg/gen/cli.py
eulerpublisher/cloudimg/gen/gen.py
eulerpublisher/container/__init__.py
eulerpublisher/container/cli.py
eulerpublisher/container/ai/__init__.py
eulerpublisher/container/ai/ai.py
eulerpublisher/container/ai/cli.py
eulerpublisher/container/base/__init__.py
eulerpublisher/container/base/base.py
eulerpublisher/container/base/cli.py
eulerpublisher/publisher/__init__.py
eulerpublisher/publisher/publisher.py