Metadata-Version: 2.1
Name: eulerpublisher
Version: 0.0.3
Summary: An unified toolset to publish openEuler images, including container, cloud, WSL etc.
Home-page: https://gitee.com/openeuler/eulerpublisher
Author: openEUler Infra SIG
License: UNKNOWN
Platform: UNKNOWN
Classifier: Intended Audience :: Information Technology
Classifier: Intended Audience :: System Administrators
Classifier: License :: OSI Approved :: Mulan Permissive Software License v2 (MulanPSL-2.0)
Classifier: Operating System :: POSIX :: Linux
Classifier: Programming Language :: Python
Classifier: Programming Language :: Python :: 3
Classifier: Programming Language :: Python :: 3.7
Classifier: Programming Language :: Python :: 3.8
Classifier: Programming Language :: Python :: 3.9
Requires-Python: >=3.7
